<de.ingrid.codelists.model.CodeList>
  <id>6500</id>
  <name>Lizenzen</name>
  <defaultEntry>-1</defaultEntry>
  <entries>
    <de.ingrid.codelists.model.CodeListEntry>
      <id>1</id>
      <localisations>
        <entry>
          <string>de</string>
          <string>Datenlizenz Deutschland Namensnennung</string>
        </entry>
      </localisations>
      <data>{"id":"dl-de-by-1.0","name":"Datenlizenz Deutschland Namensnennung","url":"","quelle":""}</data>
    </de.ingrid.codelists.model.CodeListEntry>
    <de.ingrid.codelists.model.CodeListEntry>
      <id>2</id>
      <localisations>
        <entry>
          <string>de</string>
          <string>Amtliches Werk, lizenzfrei nach §5 UrhG</string>
        </entry>
      </localisations>
      <data>{"id":"official-work","name":"Amtliches Werk, lizenzfrei nach §5 UrhG","url":"","quelle":""}</data>
    </de.ingrid.codelists.model.CodeListEntry>
    <de.ingrid.codelists.model.CodeListEntry>
      <id>3</id>
      <localisations>
        <entry>
          <string>de</string>
          <string>Nutzungsbestimmungen für die Bereitstellung von Geodaten des Bundes</string>
        </entry>
      </localisations>
      <data>{"id":"geonutzv-de-2013-03-19","name":"Nutzungsbestimmungen für die Bereitstellung von Geodaten des Bundes","url":"","quelle":""}</data>
    </de.ingrid.codelists.model.CodeListEntry>
    <de.ingrid.codelists.model.CodeListEntry>
      <id>4</id>
      <localisations>
        <entry>
          <string>de</string>
          <string>Creative Commons Namensnennung (CC-BY)</string>
        </entry>
      </localisations>
      <data>{"id":"cc-by","name":"Creative Commons Namensnennung (CC-BY)","url":"","quelle":""}</data>
    </de.ingrid.codelists.model.CodeListEntry>
    <de.ingrid.codelists.model.CodeListEntry>
      <id>5</id>
      <localisations>
        <entry>
          <string>de</string>
          <string>Creative Commons Zero</string>
        </entry>
      </localisations>
      <data>{"id":"cc-zero","name":"Creative Commons Zero","url":"","quelle":""}</data>
    </de.ingrid.codelists.model.CodeListEntry>
    <de.ingrid.codelists.model.CodeListEntry>
      <id>6</id>
      <localisations>
        <entry>
          <string>de</string>
          <string>Creative Commons Attribution Weitergabe unter gleichen Bedingungen (CC-BY-SA)</string>
        </entry>
      </localisations>
      <data>{"id":"cc-by-sa","name":"Creative Commons Attribution Weitergabe unter gleichen Bedingungen (CC-BY-SA)","url":"","quelle":""}</data>
    </de.ingrid.codelists.model.CodeListEntry>
    <de.ingrid.codelists.model.CodeListEntry>
      <id>7</id>
      <localisations>
        <entry>
          <string>de</string>
          <string>Open Data Commons Open Database License (ODbL)</string>
        </entry>
      </localisations>
      <data>{"id":"odc-odbl","name":"Open Data Commons Open Database License (ODbL)","url":"","quelle":""}</data>
    </de.ingrid.codelists.model.CodeListEntry>
    <de.ingrid.codelists.model.CodeListEntry>
      <id>8</id>
      <localisations>
        <entry>
          <string>de</string>
          <string>Open Data Commons Namensnennung</string>
        </entry>
      </localisations>
      <data>{"id":"odc-by","name":"Open Data Commons Namensnennung","url":"","quelle":""}</data>
    </de.ingrid.codelists.model.CodeListEntry>
    <de.ingrid.codelists.model.CodeListEntry>
      <id>9</id>
      <localisations>
        <entry>
          <string>de</string>
          <string>Open Data Commons Public Domain Dedication and Licence (PDDL)</string>
        </entry>
      </localisations>
      <data>{"id":"odc-pddl","name":"Open Data Commons Public Domain Dedication and Licence (PDDL)","url":"","quelle":""}</data>
    </de.ingrid.codelists.model.CodeListEntry>
    <de.ingrid.codelists.model.CodeListEntry>
      <id>10</id>
      <localisations>
        <entry>
          <string>de</string>
          <string>Andere freie Lizenz</string>
        </entry>
      </localisations>
      <data>{"id":"other-open","name":"Andere freie Lizenz","url":"","quelle":""}</data>
    </de.ingrid.codelists.model.CodeListEntry>
    <de.ingrid.codelists.model.CodeListEntry>
      <id>11</id>
      <localisations>
        <entry>
          <string>de</string>
          <string>Creative Commons Nicht-Kommerziell (CC-NC)</string>
        </entry>
      </localisations>
      <data>{"id":"cc-nc","name":"Creative Commons Nicht-Kommerziell (CC-NC)","url":"","quelle":""}</data>
    </de.ingrid.codelists.model.CodeListEntry>
    <de.ingrid.codelists.model.CodeListEntry>
      <id>12</id>
      <localisations>
        <entry>
          <string>de</string>
          <string>Creative Commons Keine Bearbeitung (CC-BY-ND)</string>
        </entry>
      </localisations>
      <data>{"id":"cc-by-nd","name":"Creative Commons Keine Bearbeitung (CC-BY-ND)","url":"","quelle":""}</data>
    </de.ingrid.codelists.model.CodeListEntry>
    <de.ingrid.codelists.model.CodeListEntry>
      <id>13</id>
      <localisations>
        <entry>
          <string>de</string>
          <string>Datenlizenz Deutschland Namensnennung nicht-kommerziell</string>
        </entry>
      </localisations>
      <data>{"id":"dl-de-by-nc-1.0","name":"Datenlizenz Deutschland Namensnennung nicht-kommerziell","url":"","quelle":""}</data>
    </de.ingrid.codelists.model.CodeListEntry>
    <de.ingrid.codelists.model.CodeListEntry>
      <id>14</id>
      <localisations>
        <entry>
          <string>de</string>
          <string>Geolizenz Ia Namensnennung</string>
        </entry>
      </localisations>
      <data>{"id":"geolizenz-i-a","name":"Geolizenz Ia Namensnennung","url":"","quelle":""}</data>
    </de.ingrid.codelists.model.CodeListEntry>
    <de.ingrid.codelists.model.CodeListEntry>
      <id>15</id>
      <localisations>
        <entry>
          <string>de</string>
          <string>eingeschränkte Geolizenz</string>
        </entry>
      </localisations>
      <data>{"id":"geolizenz-closed","name":"eingeschränkte Geolizenz","url":"","quelle":""}</data>
    </de.ingrid.codelists.model.CodeListEntry>
    <de.ingrid.codelists.model.CodeListEntry>
      <id>16</id>
      <localisations>
        <entry>
          <string>de</string>
          <string>Apache Lizenz</string>
        </entry>
      </localisations>
      <data>{"id":"apache","name":"Apache Lizenz","url":"","quelle":""}</data>
    </de.ingrid.codelists.model.CodeListEntry>
    <de.ingrid.codelists.model.CodeListEntry>
      <id>17</id>
      <localisations>
        <entry>
          <string>de</string>
          <string>Andere kommerzielle Lizenz</string>
        </entry>
      </localisations>
      <data>{"id":"app_commercial","name":"Andere kommerzielle Lizenz","url":"","quelle":""}</data>
    </de.ingrid.codelists.model.CodeListEntry>
    <de.ingrid.codelists.model.CodeListEntry>
      <id>18</id>
      <localisations>
        <entry>
          <string>de</string>
          <string>Andere kostenfreie Lizenz</string>
        </entry>
      </localisations>
      <data>{"id":"app_freeware","name":"Andere kostenfreie Lizenz","url":"","quelle":""}</data>
    </de.ingrid.codelists.model.CodeListEntry>
    <de.ingrid.codelists.model.CodeListEntry>
      <id>19</id>
      <localisations>
        <entry>
          <string>de</string>
          <string>Andere Open Source Lizenz</string>
        </entry>
      </localisations>
      <data>{"id":"app_opensource","name":"Andere Open Source Lizenz","url":"","quelle":""}</data>
    </de.ingrid.codelists.model.CodeListEntry>
    <de.ingrid.codelists.model.CodeListEntry>
      <id>20</id>
      <localisations>
        <entry>
          <string>de</string>
          <string>BSD Lizenz</string>
        </entry>
      </localisations>
      <data>{"id":"bsd-license","name":"BSD Lizenz","url":"","quelle":""}</data>
    </de.ingrid.codelists.model.CodeListEntry>
    <de.ingrid.codelists.model.CodeListEntry>
      <id>21</id>
      <localisations>
        <entry>
          <string>de</string>
          <string>GNU Free Documentation License</string>
        </entry>
      </localisations>
      <data>{"id":"gfdl","name":"GNU Free Documentation License","url":"","quelle":""}</data>
    </de.ingrid.codelists.model.CodeListEntry>
    <de.ingrid.codelists.model.CodeListEntry>
      <id>22</id>
      <localisations>
        <entry>
          <string>de</string>
          <string>GNU General Public License version 3.0 (GPLv3)</string>
        </entry>
      </localisations>
      <data>{"id":"gpl-3.0","name":"GNU General Public License version 3.0 (GPLv3)","url":"","quelle":""}</data>
    </de.ingrid.codelists.model.CodeListEntry>
    <de.ingrid.codelists.model.CodeListEntry>
      <id>23</id>
      <localisations>
        <entry>
          <string>de</string>
          <string>Mozilla Public License 1.0 (MPL)</string>
        </entry>
      </localisations>
      <data>{"id":"mozilla","name":"Mozilla Public License 1.0 (MPL)","url":"","quelle":""}</data>
    </de.ingrid.codelists.model.CodeListEntry>
    <de.ingrid.codelists.model.CodeListEntry>
      <id>24</id>
      <localisations>
        <entry>
          <string>de</string>
          <string>Andere eingeschränkte Lizenz</string>
        </entry>
      </localisations>
      <data>{"id":"other-closed","name":"Andere eingeschränkte Lizenz","url":"","quelle":""}</data>
    </de.ingrid.codelists.model.CodeListEntry>
  </entries>
</de.ingrid.codelists.model.CodeList>
