<de.ingrid.codelists.model.CodeList>
  <id>1230</id>
  <name>Zeitbezug - Alle...</name>
  <defaultEntry></defaultEntry>
  <entries>
    <de.ingrid.codelists.model.CodeListEntry>
      <id>1</id>
      <localisations>
        <entry>
          <string>de</string>
          <string>Sekunden</string>
        </entry>
        <entry>
          <string>en</string>
          <string>Seconds</string>
        </entry>
      </localisations>
    </de.ingrid.codelists.model.CodeListEntry>
    <de.ingrid.codelists.model.CodeListEntry>
      <id>2</id>
      <localisations>
        <entry>
          <string>de</string>
          <string>Minuten</string>
        </entry>
        <entry>
          <string>en</string>
          <string>Minutes</string>
        </entry>
      </localisations>
    </de.ingrid.codelists.model.CodeListEntry>
    <de.ingrid.codelists.model.CodeListEntry>
      <id>3</id>
      <localisations>
        <entry>
          <string>de</string>
          <string>Stunden</string>
        </entry>
        <entry>
          <string>en</string>
          <string>Hours</string>
        </entry>
      </localisations>
    </de.ingrid.codelists.model.CodeListEntry>
    <de.ingrid.codelists.model.CodeListEntry>
      <id>4</id>
      <localisations>
        <entry>
          <string>de</string>
          <string>Tage</string>
        </entry>
        <entry>
          <string>en</string>
          <string>Days</string>
        </entry>
      </localisations>
    </de.ingrid.codelists.model.CodeListEntry>
    <de.ingrid.codelists.model.CodeListEntry>
      <id>5</id>
      <localisations>
        <entry>
          <string>de</string>
          <string>Monate</string>
        </entry>
        <entry>
          <string>en</string>
          <string>Months</string>
        </entry>
      </localisations>
    </de.ingrid.codelists.model.CodeListEntry>
    <de.ingrid.codelists.model.CodeListEntry>
      <id>6</id>
      <localisations>
        <entry>
          <string>de</string>
          <string>Jahre</string>
        </entry>
        <entry>
          <string>en</string>
          <string>Years</string>
        </entry>
      </localisations>
    </de.ingrid.codelists.model.CodeListEntry>
  </entries>
</de.ingrid.codelists.model.CodeList>
